[
  {
    "full_name": "appwrite/appwrite",
    "stargazers_count": 12011,
    "open_issues_count": 359,
    "forks_count": 929
  },
  {
    "full_name": "open-sauced/open-sauced",
    "stargazers_count": 492,
    "open_issues_count": 32,
    "forks_count": 143
  },
  {
    "full_name": "shuding/nextra",
    "stargazers_count": 2219,
    "open_issues_count": 76,
    "forks_count": 266
  },
  {
    "full_name": "Kholid060/projectile",
    "stargazers_count": 61,
    "open_issues_count": 0,
    "forks_count": 4
  },
  {
    "full_name": "swc-project/swc",
    "stargazers_count": 15408,
    "open_issues_count": 155,
    "forks_count": 429
  },
  {
    "full_name": "blitz-js/blitz",
    "stargazers_count": 9344,
    "open_issues_count": 135,
    "forks_count": 529
  },
  {
    "full_name": "vercel/next.js",
    "stargazers_count": 73751,
    "open_issues_count": 1125,
    "forks_count": 14523
  }
]